LICENSE.txt
MANIFEST.in
README.rst
setup.py
brick_wall_build/__init__.py
brick_wall_build/_brick_wall_build.py
brick_wall_build.egg-info/PKG-INFO
brick_wall_build.egg-info/SOURCES.txt
brick_wall_build.egg-info/dependency_links.txt
brick_wall_build.egg-info/entry_points.txt
brick_wall_build.egg-info/requires.txt
brick_wall_build.egg-info/top_level.txt