Metadata-Version: 1.1
Name: brick-wall-build
Version: 0.0.1a.dev3
Summary: Lightweight Python Build Tool.
Home-page: https://github.com/IndeedTokyo-BrickWall/brick-wall-build
Author: Artem Onuchin
Author-email: onuchinart@gmail.com
License: MIT License
Platform: UNKNOWN
Classifier: Development Status :: 3 - Alpha
Classifier: Intended Audience :: Developers
Classifier: Topic :: Software Development :: Build Tools
Classifier: License :: OSI Approved :: MIT License
Classifier: Programming Language :: Python :: 2
Classifier: Programming Language :: Python :: 2.7
